build/lib/examples/batched_experiment/batched_experiment.py
build/lib/examples/semantic_mapper/semantic_mapper.py
build/lib/test/fake_representation.py
build/lib/test/integration/test_no_vre_setup_if_not_needed.py
build/lib/test/integration/test_vre.py
build/lib/test/integration/test_vre_batched.py
build/lib/test/integration/test_vre_taskmapped_representations.py
build/lib/test/integration/readers/test_multitask_dataset.py
build/lib/test/integration/representations/semantic_segmentation/test_i_mask2former.py
build/lib/test/integration/representations/soft_segmentation/test_i_fastsam.py
build/lib/test/unit/test_data_writer_storer.py
build/lib/test/unit/test_vre_runtime_args.py
build/lib/test/unit/representations/test_build_representations.py
build/lib/test/unit/representations/test_representation.py
build/lib/test/unit/representations/color/test_hsv.py
build/lib/test/unit/representations/color/test_rgb.py
build/lib/test/unit/representations/depth/test_dpt.py
build/lib/test/unit/representations/depth/test_marigold.py
build/lib/test/unit/representations/edges/test_canny.py
build/lib/test/unit/representations/edges/test_dexined.py
build/lib/test/unit/representations/normals/test_depth_normals_svd.py
build/lib/test/unit/representations/optical_flow/test_raft.py
build/lib/test/unit/representations/optical_flow/test_rife.py
build/lib/test/unit/representations/semantic_segmentation/test_mask2former.py
build/lib/test/unit/representations/semantic_segmentation/test_safeuav.py
build/lib/test/unit/representations/soft_segmentation/test_fastssam.py
build/lib/test/unit/representations/soft_segmentation/test_generalized_boundaries.py
build/lib/test/unit/representations/soft_segmentation/test_halftone.py
build/lib/test/unit/utils/test_fake_video.py
build/lib/vre/__init__.py
build/lib/vre/data_storer.py
build/lib/vre/data_writer.py
build/lib/vre/logger.py
build/lib/vre/metadata.py
build/lib/vre/video_representations_extractor.py
build/lib/vre/vre_runtime_args.py
video_representations_extractor-1.5.16.dist-info/LICENSE.TXT
video_representations_extractor-1.5.16.dist-info/METADATA
video_representations_extractor-1.5.16.dist-info/WHEEL
video_representations_extractor-1.5.16.dist-info/top_level.txt
video_representations_extractor-1.5.16.dist-info/RECORD
